{
    "Id": "",
    "Version": "v1.0.16",
    "Type": 0,
    "AccessRight": 0,
    "DownloadUrl": "",
    "InstallPath": "Assets/QFramework/Framework/",
    "IncludeFileOrFolders": [
        "Assets/QFramework/Framework",
        "Assets/QFramework/Toolkits"
    ],
    "DocUrl": "https://liangxiegame.com",
    "Readme": {
        "version": "v1.0.16",
        "content": "ResKit：修复在非模拟模式下无法异步加载场景的问题",
        "author": "liangxie",
        "date": "2022 年 11 月 10 日 16:54",
        "PackageId": ""
    }
}